anki_utils/CHANGELOG.md
anki_utils/MIGRATIONS.md
anki_utils/ROADMAP.md
anki_utils/SKILL_UPDATE_PROTOCOL.md
anki_utils/__init__.py
anki_utils/cli.py
anki_utils/dev_tools.py
anki_utils/exporter.py
anki_utils/markdown.py
anki_utils/occlusion.py
anki_utils/themes.py
anki_utils/assets/preview-template.jsx
anki_utils/assets/pure-functions.js
anki_utils/assets/shared-preview.jsx
anki_utils/assets/theme-designer.jsx
anki_utils/assets/bundled/preview-template.jsx
anki_utils/assets/bundled/theme-designer.jsx
anki_utils-0.2.92.dist-info/METADATA
anki_utils-0.2.92.dist-info/WHEEL
anki_utils-0.2.92.dist-info/entry_points.txt
anki_utils-0.2.92.dist-info/top_level.txt
anki_utils-0.2.92.dist-info/RECORD
