Metadata-Version: 2.4
Name: anki-utils
Version: 0.2.92
Summary: Python utilities for creating Anki flashcards. Designed for AI agent integration.
License: MIT
Project-URL: Homepage, https://pypi.org/project/anki-utils/
Requires-Python: >=3.9
Requires-Dist: genanki
Requires-Dist: Pillow
Requires-Dist: pytesseract
Provides-Extra: dev
Requires-Dist: pytest>=7.0; extra == "dev"
Requires-Dist: pytest-cov>=4.0; extra == "dev"
Requires-Dist: towncrier>=23.0; extra == "dev"
